setup.py
distributions_pkg_rename/Binomialdistribution.py
distributions_pkg_rename/Gaussiandistribution.py
distributions_pkg_rename/Generaldistribution.py
distributions_pkg_rename/__init__.py
distributions_pkg_rename.egg-info/PKG-INFO
distributions_pkg_rename.egg-info/SOURCES.txt
distributions_pkg_rename.egg-info/dependency_links.txt
distributions_pkg_rename.egg-info/not-zip-safe
distributions_pkg_rename.egg-info/top_level.txt